havoc_clustering/__init__.py
havoc_clustering/correlation_of_dlfv_groups.py
havoc_clustering/havoc.py
havoc_clustering/requirements.txt
havoc_clustering/general_utility/image_creator.py
havoc_clustering/general_utility/print_time.py
havoc_clustering/general_utility/slide.py
havoc_clustering/general_utility/tile_image_utils.py
havoc_clustering/general_utility/unique_colors.py
havoc_clustering/general_utility/ai/model_utils.py
havoc_clustering/general_utility/ai/tileextractor.py
havoc_clustering-0.0.20.dist-info/METADATA
havoc_clustering-0.0.20.dist-info/WHEEL
havoc_clustering-0.0.20.dist-info/licenses/LICENSE
havoc_clustering-0.0.20.dist-info/RECORD
